HowtodoinjavaQitaJiaocheng1ChuyiFix1/README.md
HowtodoinjavaQitaJiaocheng1ChuyiFix1/__init__.py
HowtodoinjavaQitaJiaocheng1ChuyiFix1/__main__.py
HowtodoinjavaQitaJiaocheng1ChuyiFix1/file.epub
HowtodoinjavaQitaJiaocheng1ChuyiFix1/index.html
HowtodoinjavaQitaJiaocheng1ChuyiFix1/css/__init__.py
HowtodoinjavaQitaJiaocheng1ChuyiFix1/css/annotations.css
HowtodoinjavaQitaJiaocheng1ChuyiFix1/css/main.css
HowtodoinjavaQitaJiaocheng1ChuyiFix1/css/normalize.css
HowtodoinjavaQitaJiaocheng1ChuyiFix1/css/popup.css
HowtodoinjavaQitaJiaocheng1ChuyiFix1/font/__init__.py
HowtodoinjavaQitaJiaocheng1ChuyiFix1/font/fontello.eot
HowtodoinjavaQitaJiaocheng1ChuyiFix1/font/fontello.svg
HowtodoinjavaQitaJiaocheng1ChuyiFix1/font/fontello.ttf
HowtodoinjavaQitaJiaocheng1ChuyiFix1/font/fontello.woff
HowtodoinjavaQitaJiaocheng1ChuyiFix1/img/__init__.py
HowtodoinjavaQitaJiaocheng1ChuyiFix1/img/annotator-glyph-sprite.png
HowtodoinjavaQitaJiaocheng1ChuyiFix1/img/annotator-icon-sprite.png
HowtodoinjavaQitaJiaocheng1ChuyiFix1/img/apple-touch-icon.png
HowtodoinjavaQitaJiaocheng1ChuyiFix1/img/cancelfullscreen.png
HowtodoinjavaQitaJiaocheng1ChuyiFix1/img/close.png
HowtodoinjavaQitaJiaocheng1ChuyiFix1/img/fullscreen.png
HowtodoinjavaQitaJiaocheng1ChuyiFix1/img/loader.gif
HowtodoinjavaQitaJiaocheng1ChuyiFix1/img/menu-icon.png
HowtodoinjavaQitaJiaocheng1ChuyiFix1/img/save.png
HowtodoinjavaQitaJiaocheng1ChuyiFix1/img/saved.png
HowtodoinjavaQitaJiaocheng1ChuyiFix1/img/settings-s.png
HowtodoinjavaQitaJiaocheng1ChuyiFix1/img/settings.png
HowtodoinjavaQitaJiaocheng1ChuyiFix1/img/star.png
HowtodoinjavaQitaJiaocheng1ChuyiFix1/js/__init__.py
HowtodoinjavaQitaJiaocheng1ChuyiFix1/js/epub.js
HowtodoinjavaQitaJiaocheng1ChuyiFix1/js/epub.min.js
HowtodoinjavaQitaJiaocheng1ChuyiFix1/js/epub.min.map
HowtodoinjavaQitaJiaocheng1ChuyiFix1/js/hooks.min.js
HowtodoinjavaQitaJiaocheng1ChuyiFix1/js/hooks.min.map
HowtodoinjavaQitaJiaocheng1ChuyiFix1/js/reader.js
HowtodoinjavaQitaJiaocheng1ChuyiFix1/js/reader.js.map
howtodoinjava_qita_jiaocheng_1_chuyi_fix1-2025.3.24.0.dist-info/METADATA
howtodoinjava_qita_jiaocheng_1_chuyi_fix1-2025.3.24.0.dist-info/WHEEL
howtodoinjava_qita_jiaocheng_1_chuyi_fix1-2025.3.24.0.dist-info/entry_points.txt
howtodoinjava_qita_jiaocheng_1_chuyi_fix1-2025.3.24.0.dist-info/top_level.txt
howtodoinjava_qita_jiaocheng_1_chuyi_fix1-2025.3.24.0.dist-info/RECORD
